dora_mujoco/__init__.py
dora_mujoco/__main__.py
dora_mujoco/main.py
dora_mujoco-0.1.0.dist-info/METADATA
dora_mujoco-0.1.0.dist-info/WHEEL
dora_mujoco-0.1.0.dist-info/entry_points.txt
dora_mujoco-0.1.0.dist-info/top_level.txt
dora_mujoco-0.1.0.dist-info/RECORD
