Metadata-Version: 2.4
Name: dora-mujoco
Version: 0.1.0
Summary: MuJoCo simulation node for Dora
Author-email: Your Name <email@email.com>
License: MIT
Requires-Python: >=3.8
Requires-Dist: dora-rs>=0.3.9
Requires-Dist: mujoco>=3.1.6
Requires-Dist: numpy>=1.21.0
Requires-Dist: pyarrow>=14.0.1
Requires-Dist: robot_descriptions
